midb_tool/__init__.py
midb_tool/main.py
midb_tool-0.1.1.dist-info/METADATA
midb_tool-0.1.1.dist-info/WHEEL
midb_tool-0.1.1.dist-info/entry_points.txt
midb_tool-0.1.1.dist-info/RECORD
